omg_dosimetry/OMG_Logo.png
omg_dosimetry/__init__.py
omg_dosimetry/analysis.py
omg_dosimetry/calibration.py
omg_dosimetry/i_o.py
omg_dosimetry/imageRGB.py
omg_dosimetry/tiff2dose.py
omg_dosimetry/tools.py
omg_dosimetry-1.8.1.dist-info/METADATA
omg_dosimetry-1.8.1.dist-info/WHEEL
omg_dosimetry-1.8.1.dist-info/licenses/LICENSE
omg_dosimetry-1.8.1.dist-info/RECORD
