Metadata-Version: 2.4
Name: omg_dosimetry
Version: 1.8.1
Summary: Optimized Multichannel Gafchromic Dosimetry (OMG Dosimetry)
Project-URL: homepage, https://omg-dosimetry.readthedocs.io/en/latest/
Project-URL: repository, https://github.com/jfcabana/omg_dosimetry
Project-URL: Bug-Tracker, https://github.com/jfcabana/omg_dosimetry/issues
Author-email: JF Cabana <jean-francois.cabana.cisssca@ssss.gouv.qc.ca>, Peter Truong <petertruong.cissso@ssss.gouv.qc.ca>
Maintainer-email: Luis Alfonso Olivares Jimenez <alfonso.cucei.udg@gmail.com>
License-File: LICENSE
Classifier: License :: OSI Approved :: MIT License
Classifier: Operating System :: OS Independent
Classifier: Programming Language :: Python :: 3
Requires-Python: <3.11,>=3.7
Requires-Dist: pylinac~=3.7
Requires-Dist: pymedphys~=0.39
Requires-Dist: spyder~=5.3
